bigquant.py
main.py
bqmcp-0.1.1.dist-info/METADATA
bqmcp-0.1.1.dist-info/WHEEL
bqmcp-0.1.1.dist-info/top_level.txt
bqmcp-0.1.1.dist-info/RECORD
