Metadata-Version: 2.4
Name: bqmcp
Version: 0.1.1
Summary: Add your description here
Requires-Python: >=3.11
Requires-Dist: aiofiles>=24.1.0
Requires-Dist: httpx>=0.28.1
Requires-Dist: jieba>=0.42.1
Requires-Dist: mcp>=1.8.1
Requires-Dist: openai>=1.78.1
Requires-Dist: pymupdf>=1.25.5
Requires-Dist: structlog>=25.3.0
